odoo9_addon_sale_stock_medical_prescription-9.0.1.0.0-py2.7-nspkg.pth
odoo9_addon_sale_stock_medical_prescription-9.0.1.0.0.dist-info/DESCRIPTION.rst
odoo9_addon_sale_stock_medical_prescription-9.0.1.0.0.dist-info/METADATA
odoo9_addon_sale_stock_medical_prescription-9.0.1.0.0.dist-info/RECORD
odoo9_addon_sale_stock_medical_prescription-9.0.1.0.0.dist-info/WHEEL
odoo9_addon_sale_stock_medical_prescription-9.0.1.0.0.dist-info/metadata.json
odoo9_addon_sale_stock_medical_prescription-9.0.1.0.0.dist-info/namespace_packages.txt
odoo9_addon_sale_stock_medical_prescription-9.0.1.0.0.dist-info/top_level.txt
odoo_addons/sale_stock_medical_prescription/README.rst
odoo_addons/sale_stock_medical_prescription/__init__.py
odoo_addons/sale_stock_medical_prescription/__openerp__.py
odoo_addons/sale_stock_medical_prescription/hooks.py
odoo_addons/sale_stock_medical_prescription/data/stock_data.xml
odoo_addons/sale_stock_medical_prescription/demo/medical_medicament_demo.xml
odoo_addons/sale_stock_medical_prescription/demo/medical_patient_demo.xml
odoo_addons/sale_stock_medical_prescription/demo/medical_patient_medication_demo.xml
odoo_addons/sale_stock_medical_prescription/demo/medical_pharmacy_demo.xml
odoo_addons/sale_stock_medical_prescription/demo/medical_physician_demo.xml
odoo_addons/sale_stock_medical_prescription/demo/medical_prescription_order_demo.xml
odoo_addons/sale_stock_medical_prescription/demo/medical_prescription_order_line_demo.xml
odoo_addons/sale_stock_medical_prescription/demo/procurement_order_demo.xml
odoo_addons/sale_stock_medical_prescription/demo/sale_order_demo.xml
odoo_addons/sale_stock_medical_prescription/demo/sale_order_line_demo.xml
odoo_addons/sale_stock_medical_prescription/models/__init__.py
odoo_addons/sale_stock_medical_prescription/models/medical_medicament.py
odoo_addons/sale_stock_medical_prescription/models/medical_prescription_order_line.py
odoo_addons/sale_stock_medical_prescription/models/sale_order_line.py
odoo_addons/sale_stock_medical_prescription/models/stock_warehouse.py
odoo_addons/sale_stock_medical_prescription/static/description/icon.png
odoo_addons/sale_stock_medical_prescription/tests/__init__.py
odoo_addons/sale_stock_medical_prescription/tests/test_hooks.py
odoo_addons/sale_stock_medical_prescription/tests/test_medical_medicament.py
odoo_addons/sale_stock_medical_prescription/tests/test_medical_prescription_order_line.py
odoo_addons/sale_stock_medical_prescription/tests/test_sale_order_line.py
